django_mysql/__init__.py
django_mysql/apps.py
django_mysql/cache.py
django_mysql/checks.py
django_mysql/exceptions.py
django_mysql/forms.py
django_mysql/locks.py
django_mysql/operations.py
django_mysql/py.typed
django_mysql/rewrite_query.py
django_mysql/status.py
django_mysql/typing.py
django_mysql/utils.py
django_mysql/validators.py
django_mysql/management/__init__.py
django_mysql/management/commands/__init__.py
django_mysql/management/commands/cull_mysql_caches.py
django_mysql/management/commands/dbparams.py
django_mysql/management/commands/mysql_cache_migration.py
django_mysql/models/__init__.py
django_mysql/models/aggregates.py
django_mysql/models/base.py
django_mysql/models/expressions.py
django_mysql/models/functions.py
django_mysql/models/lookups.py
django_mysql/models/query.py
django_mysql/models/transforms.py
django_mysql/models/fields/__init__.py
django_mysql/models/fields/bit.py
django_mysql/models/fields/dynamic.py
django_mysql/models/fields/enum.py
django_mysql/models/fields/fixedchar.py
django_mysql/models/fields/lists.py
django_mysql/models/fields/sets.py
django_mysql/models/fields/sizes.py
django_mysql/models/fields/tiny_integer.py
django_mysql/test/__init__.py
django_mysql/test/utils.py
django_mysql-4.18.0.dist-info/licenses/LICENSE
django_mysql-4.18.0.dist-info/METADATA
django_mysql-4.18.0.dist-info/WHEEL
django_mysql-4.18.0.dist-info/top_level.txt
django_mysql-4.18.0.dist-info/RECORD
